README.md
setup.py
nemara/__init__.py
nemara/create.py
nemara/dataset_filter.py
nemara/export.py
nemara/fit.py
nemara/main.py
nemara/mara.py
nemara/meta_optimizer.py
nemara/synthetic_data.py
nemara/utils.py
nemara.egg-info/PKG-INFO
nemara.egg-info/SOURCES.txt
nemara.egg-info/dependency_links.txt
nemara.egg-info/entry_points.txt
nemara.egg-info/requires.txt
nemara.egg-info/top_level.txt